securepasslib/__init__.py
securepasslib/breach_checker.py
securepasslib/cli.py
securepasslib/generator.py
securepasslib/policy.py
securepasslib/validator.py
securepasslib/constants/__init__.py
securepasslib/constants/messages.py
securepasslib/constants/patterns.py
securepasslib/constants/presets.py
securepasslib/constants/settings.py
securepasslib/constants/templates.py
securepasslib-1.0.3.dist-info/METADATA
securepasslib-1.0.3.dist-info/WHEEL
securepasslib-1.0.3.dist-info/entry_points.txt
securepasslib-1.0.3.dist-info/top_level.txt
securepasslib-1.0.3.dist-info/RECORD
