Metadata-Version: 2.1
Name: securepasslib
Version: 1.0.3
Summary: Secure password validation, strength analysis, generation, and breach checking library
Home-page: https://github.com/mituso89/securepass
Author: Tuan Nguyen
Author-email: nguyenhuutuan1306@gmail.com
Project-URL: Documentation, https://github.com/mituso89/securepass/blob/main/docs/usage.md
Project-URL: Source, https://github.com/mituso89/securepass
Classifier: Programming Language :: Python :: 3
Classifier: License :: OSI Approved :: MIT License
Classifier: Operating System :: OS Independent
Classifier: Intended Audience :: Developers
Classifier: Topic :: Security
Classifier: Topic :: Software Development :: Libraries :: Python Modules
Requires-Python: >=3.7
Requires-Dist: requests
Requires-Dist: click
